BadWordObfuscator
