Metadata-Version: 1.0
Name: BadWordObfuscator
Version: 0.1.2
Summary: A package that helps make naughty words less visible in code.
Home-page: https://github.com/TheCuriousNerd/Bad-Word-Obfuscator
Author: Alex Orid
Author-email: inquiries@thecuriousnerd.com
License: lgpl-3.0
Platform: UNKNOWN
